flask_roleman/__init__.py
flask_roleman/group_mixing.py
flask_roleman/role_mixing.py
flask_roleman/user_mixing.py
flask_roleman-1.0.3.dist-info/METADATA
flask_roleman-1.0.3.dist-info/WHEEL
flask_roleman-1.0.3.dist-info/top_level.txt
flask_roleman-1.0.3.dist-info/RECORD
