Metadata-Version: 2.1
Name: flask-roleman
Version: 1.0.3
Summary: Flask Extension for User Authorizations, Users can have Groups, and Each Group can have Roles, more control and easy to use.
Author: Mohamed El-Hasnaouy
Author-email: <elhasnaouymed@proton.me>
Keywords: flask,extension,roles,authorization,permissions,security,groups,privileges
Classifier: Development Status :: 4 - Beta
Classifier: License :: OSI Approved :: GNU General Public License v2 (GPLv2)
Classifier: Intended Audience :: Developers
Classifier: Programming Language :: Python :: 3
Classifier: Framework :: Flask
Classifier: Topic :: Software Development :: Libraries :: Python Modules
Classifier: Operating System :: OS Independent
Requires-Dist: flask
Requires-Dist: flask-login
Requires-Dist: flask-sqlalchemy
